{
  "main": {
    "id": "64e0206fa8e429f0",
    "type": "split",
    "children": [
      {
        "id": "d679543d0e4322ec",
        "type": "tabs",
        "children": [
          {
            "id": "aedceb5c5343044b",
            "type": "leaf",
            "state": {
              "type": "markdown",
              "state": {
                "file": "Project/disorder.md",
                "mode": "source",
                "source": false
              }
            }
          },
          {
            "id": "eb60fea0124529e5",
            "type": "leaf",
            "state": {
              "type": "markdown",
              "state": {
                "file": "conflict-files-obsidian-git.md",
                "mode": "source",
                "source": false
              }
            }
          }
        ],
        "currentTab": 1
      }
    ],
    "direction": "vertical"
  },
  "left": {
    "id": "65e83c5ebf9fc976",
    "type": "split",
    "children": [
      {
        "id": "9d6dc3a45185b9a1",
        "type": "tabs",
        "children": [
          {
            "id": "2f8f6a61c23f575d",
            "type": "leaf",
            "state": {
              "type": "file-explorer",
              "state": {
                "sortOrder": "byModifiedTime"
              }
            }
          },
          {
            "id": "582751c056881189",
            "type": "leaf",
            "state": {
              "type": "search",
              "state": {
                "query": "",
                "matchingCase": false,
                "explainSearch": false,
                "collapseAll": false,
                "extraContext": false,
                "sortOrder": "alphabetical"
              }
            }
          },
          {
            "id": "dd24029204bfbae2",
            "type": "leaf",
            "state": {
              "type": "bookmarks",
              "state": {}
            }
          }
        ]
      }
    ],
    "direction": "horizontal",
    "width": 219.51103591918945
  },
  "right": {
    "id": "04ef13bda26685a2",
    "type": "split",
    "children": [
      {
        "id": "e246b4db3a123735",
        "type": "tabs",
        "children": [
          {
            "id": "86e0133c3fc56063",
            "type": "leaf",
            "state": {
              "type": "backlink",
              "state": {
                "file": "conflict-files-obsidian-git.md",
                "collapseAll": false,
                "extraContext": false,
                "sortOrder": "alphabetical",
                "showSearch": false,
                "searchQuery": "",
                "backlinkCollapsed": false,
                "unlinkedCollapsed": true
              }
            }
          },
          {
            "id": "e90e601bc8b7f713",
            "type": "leaf",
            "state": {
              "type": "outgoing-link",
              "state": {
                "file": "conflict-files-obsidian-git.md",
                "linksCollapsed": false,
                "unlinkedCollapsed": true
              }
            }
          },
          {
            "id": "8ad0c9b707c36627",
            "type": "leaf",
            "state": {
              "type": "tag",
              "state": {
                "sortOrder": "frequency",
                "useHierarchy": true
              }
            }
          },
          {
            "id": "dd9ae1caf2683543",
            "type": "leaf",
            "state": {
              "type": "outline",
              "state": {
                "file": "conflict-files-obsidian-git.md"
              }
            }
          },
          {
            "id": "abbb6a7877769cfd",
            "type": "leaf",
            "state": {
              "type": "reminder-list",
              "state": {}
            }
          }
        ],
        "currentTab": 4
      }
    ],
    "direction": "horizontal",
    "width": 300,
    "collapsed": true
  },
  "left-ribbon": {
    "hiddenItems": {
      "switcher:打开快速切换": false,
      "graph:查看关系图谱": false,
      "canvas:新建白板": false,
      "daily-notes:打开/创建今天的日记": false,
      "templates:插入模板": false,
      "command-palette:打开命令面板": false
    }
  },
  "active": "eb60fea0124529e5",
  "lastOpenFiles": [
    "Project/disorder.md",
    "Project/Universal theory.md",
    "conflict-files-obsidian-git.md",
    "code/leetcode.md",
    "Pasted image 20240619162135.png",
    "Pasted image 20240619161921.png",
    "Project/未命名.md",
    "Project/Log.md",
    "Statistical Physics/Phase Transition Theory.md",
    "Statistical Physics/Finite-size effects.md",
    "code/Git.md",
    "QMC/Monte Carlo/Cluster.md",
    "QMC/Monte Carlo",
    "Statistical Physics/Kardar/Chapter 2    Statistical fields.md",
    "Statistical Physics/Kardar/Chapter 4 The scaling hypothesis.md",
    "Statistical Physics/Kardar/Chapter 3 Fluctuations.md",
    "lecture/能带拓扑理论.md",
    "lecture/WannierTools.md",
    "lecture",
    "Project/Draft.md",
    "Project/FM-Triangle-Coupled-Model.md",
    "Project/Negativity in Coupled Model.md",
    "Statistical Physics/Kardar/Chapter 5 Perturbative renormalization group.md",
    "Many-Body/Green's Function.md",
    "Pasted image 20240429201859.png",
    "Pasted image 20240429193624.png",
    "Pasted image 20240428122915.png",
    "Pasted image 20240428105900.png",
    "Pasted image 20240428103447.png",
    "Pasted image 20240425113740.png",
    "Pic/Pasted image 20240326152948.png",
    "Task_plugin.md",
    "Pasted image 20240412174802.png",
    "code/Missing-Semester/课程信息.md",
    "code/Missing-Semester/Shell.md",
    "code/Missing-Semester",
    "Statistical Physics/Useful Formula.md",
    "Many-Body/Bosonization.md",
    "Statistical Physics/Kardar/Chapter 1    Collective behavior, from particles to fields.md",
    "code/Data Structure/MIT 6.006 2011",
    "code/Data Structure",
    "Many-Body/Interacting_Electrons_and_Quantum_Magnetism/11 Spin Wave Theory.pdf",
    "Many-Body/Interacting_Electrons_and_Quantum_Magnetism/Appendix B Linear Response and Generating Functionals.pdf",
    "Many-Body/Interacting_Electrons_and_Quantum_Magnetism/5.2 Half-Odd Integer Spin Chains/Assa Chap 5.2.pdf",
    "Many-Body/Interacting_Electrons_and_Quantum_Magnetism/5.2 Half-Odd Integer Spin Chains/1_YY_Weekly.pdf",
    "Many-Body/Interacting_Electrons_and_Quantum_Magnetism/5.1 The Antiferromagnet/L-M_theorem.pdf",
    "未命名 2.canvas",
    "未命名.canvas",
    "未命名 1.canvas",
    "未命名 4.canvas",
    "未命名 3.canvas"
  ]
}